init/__init__.py
ChecklistCombobox-1.1.dist-info/LICENSE
ChecklistCombobox-1.1.dist-info/METADATA
ChecklistCombobox-1.1.dist-info/WHEEL
ChecklistCombobox-1.1.dist-info/top_level.txt
ChecklistCombobox-1.1.dist-info/RECORD
