Metadata-Version: 2.1
Name: ChecklistCombobox
Version: 1.1
Summary: A Tkinter widget that uses Checkbutton widgets inside a Combobox widget
Home-page: https://github.com/hatfullr/ChecklistCombobox
Author: Roger Hatfull
Author-email: rogerhatfull@gmail.com
License: UNKNOWN
Platform: UNKNOWN
Classifier: Programming Language :: Python :: 3
Classifier: License :: OSI Approved :: MIT License
Classifier: Operating System :: OS Independent
Requires-Python: >=3.6
